dict/__init__.py
dict/read.py
dict/write.py
devkit_dict-9.0.0.dist-info/METADATA
devkit_dict-9.0.0.dist-info/WHEEL
devkit_dict-9.0.0.dist-info/top_level.txt
devkit_dict-9.0.0.dist-info/RECORD
